sast_fixer_mcp/__init__.py
sast_fixer_mcp/__main__.py
sast_fixer_mcp/py.typed
sast_fixer_mcp/server.py
sast_fixer_mcp/parsers/__init__.py
sast_fixer_mcp/parsers/base.py
sast_fixer_mcp/parsers/factory.py
sast_fixer_mcp/parsers/moan_parser.py
sast_fixer_mcp/parsers/qianxin_parser.py
sast_fixer_mcp-1.0.11.dist-info/METADATA
sast_fixer_mcp-1.0.11.dist-info/WHEEL
sast_fixer_mcp-1.0.11.dist-info/entry_points.txt
sast_fixer_mcp-1.0.11.dist-info/RECORD
