Metadata-Version: 2.4
Name: sast-fixer-mcp
Version: 1.0.11
Summary: SAST vulnerability fixing service for MCP
Author: zhanlu
Maintainer: zhanlu
License: MIT
Keywords: llm,mcp,sast,security,vulnerability
Classifier: Development Status :: 4 - Beta
Classifier: Environment :: Console
Classifier: Intended Audience :: Developers
Classifier: License :: OSI Approved :: MIT License
Classifier: Operating System :: OS Independent
Classifier: Programming Language :: Python :: 3.10
Classifier: Programming Language :: Python :: 3.11
Classifier: Programming Language :: Python :: 3.12
Requires-Python: >=3.10
Requires-Dist: click>=8.1.7
Requires-Dist: gitpython>=3.1.43
Requires-Dist: mcp>=1.0.0
Requires-Dist: pydantic>=2.0.0
Requires-Dist: python-docx==1.1.2
